Workbook

Sheet 0. Tuto
C3: Utilisation de l'excel :
C5: L'outil doit suivre la durée de vie du projet, par soucis de clarté, les onglets non remplis ou archivés sont à grisés pour l'archivage tandis que les onglets à jours sont à mettre en vert.
C7: - L'onglet rapport de visite est à remplir par le chef de projet suite à sa visite de site - L'onglet caractéristiques du projet est à remplir par l'ingénieur d'étude en charge du projet, la colonne la plus à droite correspond à la dernière version. À chaque mise à jour, une colonne est ajoutée et les anciennes colonnes sont conservées. - L'onglet Détails AgriPV contient un détail des caractéristiques par découpage du projet lorsque nécessaire et demandé par le chef de projet - Les onglets revue comprennent les informations essentielles du projet, directement issues de la colonne la plus à droite de l'onglet caractéristiques du projet, ils sont à figer une fois la revue susnommée validée.

Sheet 1. Rapport visite de site
C4: RAPPORT DE VISITE DE TERRAIN : | D4: [NOM DU PROJET]
C6: Auteur | K6: Notes : - Toutes les photos sauf drônes seront prises via l'application MAP Caméra GPS - Préparer le rapport en amont avant de se rendre sur site - Prévoir du temps avec l'exploitants pour avoir plus de réponses possibles - Tous les détails sont importants pour anticiper les sujets développment et constructions - Se munir des applications et outils avant la visite Ne pas oublier ses EPI
C7: Météo | Q7: Outils :
C8: Date | Q8: Metre a rubant 8 m
C9: Applications | D9: MAP Caméra GPS | E9: https://play.google.com/store/apps/details?id=com.gpsmapcamera.geotagginglocationonphoto&hl=fr | Q9: Odometre
C10: Outils | D10: Inclinomètre | E10: https://play.google.com/store/apps/details?id=net.androgames.clinometer&hl=fr | Q10: Inclinometre
D11: Mètre ruban 8 m | Q11: Drone
D12: Mètre laser | Q12: ...
D13: Drône | E13: DJI ou autre
D14: Odomètre | E14: https://play.google.com/store/apps/details?id=com.freemium.android.apps.gps.odometer&hl=fr
B15: CONTEXTE ET FONCIER
B17: Sujet | D17: Observations / Données | I17: Commentaires | K17: Méthode d'obtention & Analyse
B18: Localisation & GPS | K18: Relevé au centre de la parcelle (Smartphone).
B19: Identité Exploitant | K19: Entretien direct. Vérifier si le bail est en cours.
B20: Propriétaire = Exploitant ? | K20: Si NON, identifier les conflits d'usage potentiels.
B21: Historique & Acquisition | K21: Questionner sur l'usage passé (ex: ancienne décharge ?).
B22: Exigences Propriétaire | K22: Noter les "lignes rouges" (ex: conservation d'un bois).
B24: SITUATION & ACCÈS (LOGISTIQUE DE CHANTIER)
B26: Sujet | D26: Mesures / Constats | I26: Commentaires | K26: Méthode d'obtention & Analyse
B27: Nombre d'accès (Existant/Prévu) | K27: Compter les entrées existantes et identifier les futures. Est ce que l'état des accès est conforme ? Rajouter une carte avec les accès souhaités pour le projet
C28: Photo accès existants | D28: photo 1 | E28: photo 2 | F28: photo 3 | G28: photo 4 | H28: photo 5
B29: Rayons de braquage (m) et Largeur de voie (m) | K29: Vérifier si un convoi de 12m tourne sans empiéter. Odomètre/ mètre laser : Mesurer le point le plus étroit. (Cible > 4m).
C30: Photo de voie existante | D30: photo 1 | E30: photo 2 | F30: photo 3 | G30: photo 4 | H30: photo 5
B31: Portails et portes | D31: Type | K31: Si différents type de portillons ou portails, dimensions à communiquer communiquer le nombre
C32: Photo des portails et portillons | D32: photo 1 | E32: photo 2 | F32: photo 3 | G32: photo 4 | H32: photo 5
B33: Portance du sol | K33: Test au pied/tige : Évaluer si un 44 tonnes s'embourbe. Demander le type et les dimensions d'engins utilisés par l'exploitant.
C34: Photo des différents sols sur le site | D34: photo 1 | E34: photo 2 | F34: photo 3 | G34: photo 4 | H34: photo 5
B35: Servitudes / Tiers | K35: Chercher des boîtes aux lettres ou chemins communaux.
C36: Photo de voie existante | D36: photo 1 | E36: photo 2 | F36: photo 3 | G36: photo 4 | H36: photo 5
B37: Route(s) à proximité ouvertes au Public | K37: est ce que les routes qui mènent au site sont des routes publiques ou privées ? Utilser l'app GPS MAP CAMERA pour repérer l'emplacement des photos afin de bien se retrouver sur les plans
C38: Photo des Clôtures | D38: photo 1 | E38: photo 2 | F38: photo 3 | G38: photo 4 | H38: photo 5
B39: État des clôtures | K39: Inspection visuelle : Récupérables ou à remplacer ?
C40: Photo des Clôtures | D40: photo 1 | E40: photo 2 | F40: photo 3 | G40: photo 4 | H40: photo 5
B41: Type des clôtures | K41: est ce que l'emprise clôturée inclus des habitations ou bâtiments de l'exploitant ?
C42: Photo des Clôtures | D42: photo 1 | E42: photo 2 | F42: photo 3 | G42: photo 4 | H42: photo 5
B44: TOPOGRAPHIE & IMPLANTATION (INGÉNIERIE)
B46: Sujet | D46: Relevés | I46: Commentaire | K46: Méthode d'obtention & Analyse
B47: Pente max (%) / Azimut | K47: Smartphone (Inclinomètre) : Poser sur une règle au sol. Indiquer les détails des pentes observées
C48: Photos zone(s) de pentes identifiées | D48: photo 1 | E48: photo 2 | F48: photo 3 | G48: photo 4 | H48: photo 5
B49: Type de sol (Surface) | K49: Observation : Cailloux (battage difficile) ou sable/terre.
K50: Selectionner le type dans la liste colonne D
C51: Photos des différents sols sur site | D51: photo 1 | E51: photo 2 | F51: photo 3 | G51: photo 4 | H51: photo 5
B52: Zones de stockage chantier (m²) | K52: Identifier une zone plane min. 600m² proche de l'entrée accessibles pour les poids lourds
C53: Photos zone(s) de stockage identifiés | D53: photo 1 | E53: photo 2 | F53: photo 3 | G53: photo 4 | H53: photo 5
B54: Base Vie (m²) | K54: Zone plane pour bungalows et sanitaires (hors zone inondable). Voir la Possibilité de raccordement en eau et électricité, constater la présence d'arrivée électrique, tarif jaune.
C55: Photos Zone(s) de Base Vie identifiée(s) | D55: photo 1 | E55: photo 2 | F55: photo 3 | G55: photo 4 | H55: photo 5
B56: Hauteur des masques (m) | K56: Clinomètre : Viser le sommet des arbres au Sud/Est/Ouest. Drone : peut donner une indication approximative sur la hauteur des arbres
C57: Photo des arbres | D57: photo 1 | E57: photo 2 | F57: photo 3 | G57: photo 4 | H57: photo 5
B58: Délimitations parcellaires | K58: Chercher les bornes géomètres ou murs de clôture.
C59: Photo bornes et limites de parcelle | D59: photo 1 | E59: photo 2 | F59: photo 3 | G59: photo 4 | H59: photo 5
B60: Présence de Haie (m) | K60: Clinomètre : Viser le sommet de la haie. Voir si la haie peut géner l'accès au site ou peut se trouver sur l'emprise de construction ? Possibilité de supprimer la haie ?
C61: Photo de la haie | D61: photo 1 | E61: photo 2 | F61: photo 3 | G61: photo 4 | H61: photo 5
B62: Présence de pistes périphériques (m) | K62: Mètre ruban, mesurer largeur et constater la portance pour circulation des engins de chantier, camions de livraison et Camion SDIS
C63: Photo de la piste | D63: photo 1 | E63: photo 2 | F63: photo 3 | G63: photo 4 | H63: photo 5
B64: Présence de monument historique | K64: identifier si un monument ou vestige est présent sur site ou aux alentours. Église Chateaux , village proche ?
C65: Photo du vestige | D65: photo 1 | E65: photo 2 | F65: photo 3 | G65: photo 4 | H65: photo 5
B67: HYDROLOGIE & GESTION DES EAUX (RISQUES)
B69: Sujet | D69: Constats | I69: Commentaires | K69: Méthode d'obtention & Analyse
B70: Zones Humides / Flores | K70: Chercher : Joncs, Saules, Roseaux (Zone inconstructible).
C71: Photo de la ZH | D71: photo 1 | E71: photo 2 | F71: photo 3 | G71: photo 4 | H71: photo 5
B72: Fossé & Annelé & Buses | K72: Vérifier si les buses sont curées ou écrasées.
C73: Photo des fossés et buses | D73: photo 1 | E73: photo 2 | F73: photo 3 | G73: photo 4 | H73: photo 5
B74: Zones inondables identifiées | K74: identifiées sur le terrain de la zone inondée ? quelles périodes de l'année?
C75: Photo des zones inondables | D75: photo 1 | E75: photo 2 | F75: photo 3 | G75: photo 4 | H75: photo 5
B76: Traces d'érosion | K76: Chercher des ravines ou dépôts de sédiments au sol.
C77: Photo des traces | D77: photo 1 | E77: photo 2 | F77: photo 3 | G77: photo 4 | H77: photo 5
B78: Drains agricoles | K78: Demander un plan de drain àl'exploitant
C79: Photo des drains | D79: photo 1 | E79: photo 2 | F79: photo 3 | G79: photo 4 | H79: photo 5
B80: Mares pour Canard ou autres | K80: Vérifier présence de trop-plein et son évacuation
C81: Photo des mares | D81: photo 1 | E81: photo 2 | F81: photo 3 | G81: photo 4 | H81: photo 5
B83: ENVIRONNEMENT, BÂTI & VOISINAGE
B85: Sujet | D85: Détails | I85: Commentaires | K85: Méthode d'obtention & Analyse
B86: Bâtis à démolir / Volières | K86: Mesurer au mètre ruban (Volume de déchets à évacuer).
C87: Photo des batis et volières | D87: photo Façade N | E87: photo Façade S | F87: photo Façade E | G87: photo Façade O | H87: photo toiture Drone | K87: Prendre en photo toute les façades des bâtiments. Prendre en photos les Volières
B88: Amiante présumée | K88: Photo des toitures fibro (Gris ondulé = Risque CAPEX).
C89: Photo des batis et volières | D89: photo 1 | E89: photo 2 | F89: photo 3 | G89: photo 4 | H89: photo 5 | K89: Photos des dalles bétons des bâtiment de rattrappage si présents
B90: Distance Voisinage (m) | K90: Smartphone : Estimer la distance à la première fenêtre.
C91: Photo des batis et volières | D91: photo 1 | E91: photo 2 | F91: photo 3 | G91: photo 4 | H91: photo 5
B92: Décharges sauvages | K92: Repérer les dépôts de pneus, ferrailles, gravats ou bidons.
C93: Photo des décharges | D93: photo 1 | E93: photo 2 | F93: photo 3 | G93: photo 4 | H93: photo 5
B94: Présence de SAS de sécurité et bio-sécurité | K94: Identifier la présence de SAS de sécurité et Bio-sécurité avant accès à l'exploitation
C95: Photo du SAS | D95: photo 1 | E95: photo 2 | F95: photo 3 | G95: photo 4 | H95: photo 5
B96: Présence d'espèces ou animaux dangereux | K96: identifier la présence d'espèces ou animaux qui peuvent présenter un danger en phase de contruction ? (Par exe : serpents venimeux ou autres… Poser la question à l'exploitant puis confirmer par l'EIE)
C97: Photo des traces d'animaux si répérées | D97: photo 1 | E97: photo 2 | F97: photo 3 | G97: photo 4 | H97: photo 5
B98: Densité de la végétation | K98: Est ce qu'il y a un besoin de défrichement ou élagage ?
C99: Photo de la végétation | D99: photo 1 | E99: photo 2 | F99: photo 3 | G99: photo 4 | H99: photo 5
B101: CONTRAINTES AGRICOLES (AGRI-PV / COMPATIBILITÉ)
B103: Sujet | D103: Détails | I103: Commentaires | K103: Méthode d'obtention & Analyse
B104: Gabarit Engins (m / T) | K104: Demander la largeur des engins les plus larges, lourds et hauts
C105: Photo des engins | D105: photo 1 | E105: photo 2 | F105: photo 3 | G105: photo 4 | H105: photo 5
B106: Système d'irrigation / abreuvage | K106: Localiser les têtes de vannes (Risque lors du battage).
C107: Photo des bornes | D107: photo 1 | E107: photo 2 | F107: photo 3 | G107: photo 4 | H107: photo 5 | K107: Identifier si les réseaux sont aériens ou enterrés
B108: Type de culture/élevage | K108: Définir la hauteur sous table nécessaire (ex: 2.5m bovin).
C109: Photo des élevages | D109: photo 1 | E109: photo 2 | F109: photo 3 | G109: photo 4 | H109: photo 5
B110: Zones de stockage agricole | K110: Est ce que l'exploitant prévoit la construction d'autres bâtiments, préaux ?
C111: Photo de la zone de stockage | D111: photo 1 | E111: photo 2 | F111: photo 3 | G111: photo 4 | H111: photo 5
B112: Contraintes particulières exploitants | K112: En commentaire, décrire le planning d'activité agricole sur l'année
C113: Photo des contraintes | D113: photo 1 | E113: photo 2 | F113: photo 3 | G113: photo 4 | H113: photo 5
B115: RÉSEAUX & POSITIONNEMENT ÉLECTRIQUE (PTR/PDL)
B117: Sujet | D117: Constats / Relevés | I117: Commentaires | K117: Méthode d'obtention & Analyse Expert
...

Sheet 2. Caractéristiques du projet
A1: Projet Saint-Cyr-en-Val | B1: IND05 | C1: IND06
A2: Phase | B2: APS | C2: APS
A3: Date (jj/mm/aaaa) | B3: 46071 | C3: 46259
A6: GENERALITES
A7: Type de projet | B7: Agri compatible | C7: Agri compatible
A8: Surface clôturée (ha) | B8: 4.52 | C8: 4.52
A9: Linéaire de clôture (m) | B9: 875 | C9: 875
A10: Nombre de portails d'accès | B10: 3 | C10: 3
A11: Largeur des portails (m) | B11: 7 | C11: 7
A13: SYSTÈME PHOTOVOLTAÏQUE
A14: Structures PV
A15: Type de structure | B15: Fixe | C15: Fixe
A16: Format table | B16: 2V | C16: 2V
A17: Inclinaison (°) | B17: =HLOOKUP($B$7,'Standards UNITe'!$C$3:$L$8,3,0) -> 15 | C17: =HLOOKUP($B$7,'Standards UNITe'!$C$3:$L$8,3,0) -> 15
A18: Azimut (°) | B18: =HLOOKUP($B$7,'Standards UNITe'!$C$3:$L$8,4,0) -> 0° | C18: =HLOOKUP($B$7,'Standards UNITe'!$C$3:$L$8,4,0) -> 0°
A19: Nombre de tables | B19: =21+105 -> 126 | C19: =14+82 -> 96
A20: Inter-table (m) | B20: 3 | C20: 4.9
A21: Pitch (m) | B21: 7.6 | C21: 9.5
A22: Point bas (m) | B22: 2.5 | C22: 2.5
A23: Point haut (m) | B23: 4 | C23: 4
A24: Nb de mod en rampant | B24: 2 | C24: 2
A25: Nb de mod en longueur | B25: 13 / 26 | C25: 13 / 26
A26: Nb de mod/string | B26: 26 | C26: 26
A27: Nb de mod/table | B27: 26 / 52 | C27: 26 / 52
A28: Type de fondation | B28: Pieux battus | C28: Pieux battus
A29: Nombre de pieux | B29: =105*8+5*21 -> 945 | C29: =82*8+14*21 -> 950
A30: Surface pieux (m²) | B30: =B29*IF(B15="Flotteur",0,IF(OR(B7="Volailles",B7="Faisans",B7="Parking"),VLOOKUP(B28,'Dimensions postes et pieux'!$O$5:$P$8, 2, 0),VLOOKUP(B28,'Dimensions postes et pieux'!$O$9:$P$12, 2, 0))) -> 6.615 | C30: =C29*IF(C15="Flotteur",0,IF(OR(C7="Volailles",C7="Faisans",C7="Parking"),VLOOKUP(C28,'Dimensions postes et pieux'!$O$5:$P$8, 2, 0),VLOOKUP(C28,'Dimensions postes et pieux'!$O$9:$P$12, 2, 0))) -> 6.65
A31: Modules PV
A32: Format | B32: G12R | C32: G12R
A33: Puissance unitaire (Wc) | B33: 665 | C33: 635
A34: Surface unitaire (m²) | B34: =IF(B32="G12R", 2.382*1.134, 2.382*1.303) -> 2.701188 | C34: =IF(C32="G12R", 2.382*1.134, 2.382*1.303) -> 2.701188
A35: Nombre installé | B35: 6006 | C35: 4628
A36: GCR (%) | B36: {=(2.382*(_xlfn._xlws.FILTER(VALUE(MID(B16,_xlfn.SEQUENCE(,LEN(B16)),1)),ISNUMBER(VALUE(MID(B16,_xlfn.SEQUENCE(,LEN(B16)),1)))))+0.02*(_xlfn._xlws.FILTER(VALUE(MID(B16,_xlfn.SEQUENCE(,LEN(B16)),1)),ISNUMBER(VALUE(MID(B16,_xlfn.SEQUENCE(,LEN(B16)),1))))-1))/B21} -> 0.62947368 | C36: {=(2.382*(_xlfn._xlws.FILTER(VALUE(MID(C16,_xlfn.SEQUENCE(,LEN(C16)),1)),ISNUMBER(VALUE(MID(C16,_xlfn.SEQUENCE(,LEN(C16)),1)))))+0.02*(_xlfn._xlws.FILTER(VALUE(MID(C16,_xlfn.SEQUENCE(,LEN(C16)),1)),ISNUMBER(VALUE(MID(C16,_xlfn.SEQUENCE(,LEN(C16)),1))))-1))/C21} -> 0.50357895
A37: Surface modules (m²) | B37: =IFERROR(B34*B35,"-") -> 16223.335 | C37: =IFERROR(C34*C35,"-") -> 12501.098
A38: Surface module projetée au sol (m²) | B38: =IFERROR(B37*COS(RADIANS(B17)),"-") -> 15670.538 | C38: =IFERROR(C37*COS(RADIANS(C17)),"-") -> 12075.133
A39: Puissance projet (MWc) | B39: =IFERROR(B33*B35/1000000,"-") -> 3.99399 | C39: =IFERROR(C33*C35/1000000,"-") -> 2.93878
A42: POSTES ELEC. ET LOCAUX TECHNIQUES
A43: Postes élec.
A44: Type d'onduleurs envisagés | B44: String | C44: String
A45: Nombre de PTR | B45: 0 | C45: 0
A46: Surface des PTR (m²) | B46: =B45*'Dimensions postes et pieux'!$D$5 -> 0 | C46: =C45*'Dimensions postes et pieux'!$D$5 -> 0
A47: Surface plateforme PTR (m²) | B47: =B45*'Dimensions postes et pieux'!$E$5 -> 0 | C47: =C45*'Dimensions postes et pieux'!$E$5 -> 0
A48: Nombre de PDL /PTR | B48: 1 | C48: 1
A49: Surface des PDL/PTR (m²) | B49: =B48*(36+1.5*12+1*12) -> 66 | C49: =C48*(36+1.5*12+1*12) -> 66
A50: Surface plateforme PDL/PTR (m²) | B50: =B48*'Dimensions postes et pieux'!$E$17 -> 132 | C50: =C48*'Dimensions postes et pieux'!$E$17 -> 132
A51: Nombre de PDL | B51: 0 | C51: 0
A52: Surface des PDL (m²) | B52: =B51*'Dimensions postes et pieux'!$D$23 -> 0 | C52: =C51*'Dimensions postes et pieux'!$D$23 -> 0
A53: Surface plateforme PDL (m²) | B53: =B51*'Dimensions postes et pieux'!$E$23 -> 0 | C53: =C51*'Dimensions postes et pieux'!$E$23 -> 0
A54: Aire de charge (BESS)
A55: Nombre de conteneurs de batteries | B55: 0 | C55: 0
A56: Surface des conteneurs (m²) | B56: =B55*'Dimensions postes et pieux'!$D$29 -> 0 | C56: =C55*'Dimensions postes et pieux'!$D$29 -> 0
A57: Surface plateforme batteries (m²) | B57: =B55*'Dimensions postes et pieux'!$E$29 -> 0 | C57: =C55*'Dimensions postes et pieux'!$E$29 -> 0
A58: Nombre de PTR associés | B58: 0 | C58: 0
A59: Surface PTR associés | B59: =B58*'Dimensions postes et pieux'!$D$5 -> 0 | C59: =C58*'Dimensions postes et pieux'!$D$5 -> 0
A60: Surface plateforme PTR associés (m²) | B60: =B58*'Dimensions postes et pieux'!$E$5 -> 0 | C60: =C58*'Dimensions postes et pieux'!$E$5 -> 0
A61: Citerne de refroidissement (120m3) | B61: 0 | C61: 0
A62: Bac de rétention (120m3) | B62: 0 | C62: 0
A63: Zone de remise (m²) | B63: 0 | C63: 0
A64: Stockage matériel
A65: Nombre de locaux de stockage matériel | B65: 1 | C65: 1
A66: Surface locaux de stockage matériel (m²) | B66: 18 | C66: 18
A67: TOTAL
A68: Surface postes, stockage, batteries, citerne (m²) | B68: =B49+B46+B52+B56+B59+B66+B61*'Dimensions postes et pieux'!$D$31+B63*'Dimensions postes et pieux'!$D$33+B62*'Dimensions postes et pieux'!$D$32 -> 84 | C68: =C49+C46+C52+C56+C59+C66+C61*'Dimensions postes et pieux'!$D$31+C63*'Dimensions postes et pieux'!$D$33+C62*'Dimensions postes et pieux'!$D$32 -> 84
A69: Surface plateformes, stockage, batteries, citerne (m²) | B69: =B49+B47+B53+B57+B60+B66+B61*'Dimensions postes et pieux'!$D$31+B63*'Dimensions postes et pieux'!$D$33+B62*'Dimensions postes et pieux'!$D$32 -> 84 | C69: =C49+C47+C53+C57+C60+C66+C61*'Dimensions postes et pieux'!$D$31+C63*'Dimensions postes et pieux'!$D$33+C62*'Dimensions postes et pieux'!$D$32 -> 84
A72: PISTES ET DEFENSE INCENDIE
A73: Citernes incendie
A74: Nombre de citerne 30m3 | B74: 0 | C74: 0
A75: Nombre de citerne 60m3 | B75: 1 | C75: 1
A76: Nombre de citerne 120m3 | B76: 0 | C76: 0
A77: Nombre de citerne 240m3 | B77: 0 | C77: 0
A78: TOTAL
A79: Surface citerne | B79: =B74*'Dimensions postes et pieux'!$D$47+B75*'Dimensions postes et pieux'!$D$48+B76*'Dimensions postes et pieux'!$D$49+B77*'Dimensions postes et pieux'!$D$50 -> 60 | C79: =C74*'Dimensions postes et pieux'!$D$47+C75*'Dimensions postes et pieux'!$D$48+C76*'Dimensions postes et pieux'!$D$49+C77*'Dimensions postes et pieux'!$D$50 -> 60
A80: Surface aire d'aspiration | B80: =32*SUM(B74:B77) -> 32 | C80: =32*SUM(C74:C77) -> 32
A81: Pistes de circulation
A82: Surface piste lourde interne (m²) | B82: 3365 | C82: 3365
A83: Largeur piste lourde interne (m) | B83: 4 | C83: 4
A84: Linéaire piste lourde interne (ml) | B84: =B82/B83 -> 841.25 | C84: =C82/C83 -> 841.25
A85: Surface piste lourde externe (m²) | B85: 0 | C85: 0
A86: Largeur piste lourde externe (m) | B86: 3.5 | C86: 3.5
A87: Linéaire piste lourde externe (ml) | B87: =B85/B86 -> 0 | C87: =C85/C86 -> 0
A88: Surface bande à la terre (m²) | B88: 0 | C88: 0
A89: Largeur bande à la terre (m) | B89: 3.5 | C89: 3.5
A90: Linéaire bande à la terre (ml) | B90: =B88/B89 -> 0 | C90: =C88/C89 -> 0
A91: Surface piste enherbée interne (m²) | B91: 0 | C91: 0
A92: Largeur piste enherbée interne (m) | B92: 3.5 | C92: 3.5
A93: Linéaire piste enherbée interne (ml) | B93: =B91/B92 -> 0 | C93: =C91/C92 -> 0
A94: Surface piste enherbée externe (m²) | B94: 0 | C94: 0
A95: Largeur piste enherbée externe (m) | B95: 3.5 | C95: 3.5
A96: Linéaire piste enherbée externe (ml) | B96: =B94/B95 -> 0 | C96: =C94/C95 -> 0
A97: Surface piste enherbée (m²) | B97: 605 | C97: 605
A98: Largeur piste enherbée (m) | B98: 3.5 | C98: 3.5
A99: Linéaire piste enherbée (ml) | B99: =B97/B98 -> 172.85714 | C99: =C97/C98 -> 172.85714
A100: Piste d'accès au site
A101: Surface piste d'accès (m²) | B101: 0 | C101: 0
A102: Linéaire piste d'accès (ml) | B102: 3.5 | C102: 3.5
A103: Largeur piste d'accès (m) | B103: =B101/B102 -> 0 | C103: =C101/C102 -> 0
A104: Aire de grutage (12mx15m)
A105: Nombre
A106: Supplément piste lourde (m²)
A107: TOTAL
...

Sheet 3. Détails AgriPV
D3: Parcelle 1 | E3: Parcelle 2 | F3: Parcelle 3 | G3: Parcelle 4 | H3: Parcelle 5
C4: Surface PV (m²) | D4: =6734*(2.384*1.134)*COS(RADIANS('2. Caractéristiques du projet'!B17)) -> 17584.75 | E4: =6734*(2.384*1.134)*COS(RADIANS('2. Caractéristiques du projet'!B17)) -> 17584.75 | F4: =6734*(2.384*1.134)*COS(RADIANS('2. Caractéristiques du projet'!B17)) -> 17584.75 | G4: =6734*(2.384*1.134)*COS(RADIANS('2. Caractéristiques du projet'!B17)) -> 17584.75 | H4: =6734*(2.384*1.134)*COS(RADIANS('2. Caractéristiques du projet'!B17)) -> 17584.75
C5: Parcelle agricole (m²) | D5: 46769.37 | E5: 48928.56 | F5: 7064.31 | G5: 56681.33 | H5: 45246.36
C6: Surface cloturé parcelle (ha) | D6: 35.5
C7: Fondations
C8: Nombre de pieux | D8: 1554 | E8: =270*6 -> 1620 | F8: =44*6 -> 264 | G8: =319*6 -> 1914 | H8: =254*6 -> 1524
C9: Surface pieux (m²) | D9: =0.007*D8 -> 10.878 | E9: =0.007*E8 -> 11.34 | F9: =0.007*F8 -> 1.848 | G9: =0.007*G8 -> 13.398 | H9: =0.007*H8 -> 10.668
C10: Surface pieux + 20cm (m²) | D10: =0.2*D8 -> 310.8 | E10: =0.2*E8 -> 324 | F10: =0.2*F8 -> 52.8 | G10: =0.2*G8 -> 382.8 | H10: =0.2*H8 -> 304.8
C11: Postes élec.
C12: Surface plateforme PTR (m²) | D12: 115 | E12: 115 | F12: 115 | G12: 115 | H12: 115
C13: Surface plateforme PDL/PTR (m²) | D13: 132
C14: Aire de charge (BESS)
C15: Surface conteneurs batteries (m²) | D15: =18*4 -> 72
C16: Surface plateforme PTR (m²)
C17: Surface zone de remise (m²) | D17: =1*36 -> 36
C18: Surface citerne de refroidissement (m²) | D18: =1*104 -> 104
C19: Autre
C20: Surface citerne incendie (m²) | D20: =1*(60+32) -> 92
C21: Surface local de stockage matériel (m²) | D21: 36
C22: Surface pistes lourdes (m²) | D22: 4487.91 | F22: 5355.24
C23: Données agriPV
C24: Total surface non exploitable (ha) | D24: =SUM(D10:H21)/10000 -> 0.24222
C25: Total surface non exploitable (%) | D25: =D24/SUM(D6:G6) -> 0.0068230986
C26: Taux de couverture (%) | D26: =D4/D5 -> 0.3759886 | E26: =E4/E5 -> 0.35939643 | F26: =F4/F5 -> 2.4892381 | G26: =G4/G5 -> 0.31023884 | H26: =H4/H5 -> 0.38864452
C28: Calcul de la surface non exploitable pour agriPV culture Contacter la Chambre d'Agriculture pour connaître la formule à appliquer (par rapport à quelle surface ? Quel retrait par rapport aux pieux ?) C'est au chef de projet de mofifier la formule de calcul dans l'Excel.

Sheet Standards UNITe
B2: Type de projet | C2: PV sol | G2: Ombrières | J2: Flottant | K2: Trackers
B3: Type d'activité | C3: 1MWc | D3: Agri compatible | E3: Ovin | F3: Bovin | G3: Faisans | H3: Volailles | I3: Parking | J3: Flottant | K3: AgriPV élevage ou prairie | L3: AgriPV grande culture
B4: Format modules | C4: G12R | D4: G12R | E4: G12R | F4: G12R | G4: G12R | H4: G12R | I4: G12R | J4: G12R | K4: G12R | L4: G12R
B5: Inclinaison | C5: 15 | D5: 15 | E5: 25 | F5: 15 | G5: 10 | H5: 10 | I5: 10 | J5: 5 | K5: 0 | L5: 0
B6: Azimut | C6: 0° | D6: 0° | E6: 0° | F6: 0° | G6: 0° | H6: 0° | I6: 0° | J6: 0° | K6: 90° | L6: 90°
B7: Orientation | C7: portrait | D7: portrait | E7: portrait | F7: portrait | G7: portrait | H7: portrait | I7: portrait | J7: paysage | K7: portrait | L7: portrait
B8: Types de tables (portrait = V, paysage = H) | C8: 3V | D8: 3V | E8: 2V | F8: 2V | G8: 7V | H8: 6V | I8: 11V | J8: 1H | K8: 1V | L8: 2V
B9: Distance inter-table | C9: 3 | D9: 4 | E9: 8 | F9: 8 | G9: 12 | H9: 12 | I9: 6 | J9: 0,75 m | K9: 5.1 | L9: 8.2
B10: Hauteur point bas | C10: 1.1 | D10: 1.1 | E10: 1.5 | F10: 2.5 | G10: 2.5 | H10: 2.5 | I10: 3 | J10: N/A | K10: 1.1 | L10: 1.1
B11: Hauteur point haut | C11: 2.34 | D11: 2.34 | E11: 3.12 | F11: 3.74 | G11: 5.42 | H11: 5 | I11: 7.58 | J11: N/A | K11: N/A | L11: N/A
B12: Setback | C12: 5 | D12: 5 | E12: 10 | F12: 10 | G12: 5 | H12: 5 | I12: 6 | J12: 15 m par rapport aux berges | K12: 10 | L12: 10

Sheet Dimensions postes et pieux
C3: Poste de transformation - PTR | G3: -> Onduleurs et transformateur dans le même poste | O3: Fondations
C4: Dimensions (largeur x longueur x hauteur) | D4: Surface (m²) | E4: Surface plateforme (m²) | N4: Projet | O4: Type | P4: Surface (m²)
C5: 10 x 3 x 3m | D5: 30 | E5: 115 | N5: Faisans / Volaille / Parking | O5: Pieux battus | P5: 0.015
O6: +20cm | P6: 0.45
O7: Pieux Forage/Battus | P7: 0.16
O8: Longrine
C9: Transformateur - PT | G9: -> Transformateur seul dans son poste | N9: Autre | O9: Pieux battus | P9: 0.007
C10: Dimensions (largeur x longueur x hauteur) | D10: Surface (m²) | E10: Surface plateforme (m²) | O10: +20cm | P10: 0.2
C11: 6 x 3 x 3m | D11: 18 | E11: 50 | O11: Pieux Forage/Battus | P11: 0.04
O12: Longrine | P12: 0.9
C15: Poste de livraison et de transformation - PDL/PTR | G15: ->Transformateur et cellules d'arrivée Enedis dans le même poste
C16: Dimensions (longueur x largeur x hauteur) | D16: Surface (m²) | E16: Surface plateforme (m²)
C17: 12 x 3 x 3m | D17: 36 | E17: 132
C21: Poste de livraison - PDL | G21: -> Pas de transformateur dans le poste
C22: Dimensions (longueur x largeur x hauteur) | D22: Surface (m²) | E22: Surface plateforme (m²)
C23: 9 x 3 x 3m | D23: 27 | E23: 110 | G23: -> Plus de limite de surface de plancher pour les DP
C27: Aire de charge (BESS)
C28: Dimensions (longueur x largeur x hauteur) | D28: Surface (m²) | E28: Surface plateforme (m²)
B29: Conteneurs | C29: 6 x 3 x 3m | D29: 18 | E29: 50
B30: PTR | C30: 10 x 3 x 3m | D30: 30 | E30: 115
B31: Citerne de refroidissement | C31: 11,7 x 9,3 x 1 m | D31: 104
B32: Bac de rétention | C32: 17,5 x 3 x 2,3 m | D32: 53
B33: Zone de remise | C33: 12 x 3 x 3m | D33: 36
C37: Local de stockage matériel
C38: Dimensions (longueur x largeur x hauteur) | D38: Surface (m²)
B39: P<=5MWc | C39: 1 conteneur 20 pieds 6 x 3 x 3m | D39: 18
B40: P>5MWc | C40: 1 conteneur 40 pieds 12 x 3 x 3m | D40: 36
B41: P>17MWc | C41: 2 conteneurs 40 pieds 12 x 3 x 3m | D41: 72
B45: Citerne incendie
B46: Volume [m3] | C46: Dimensions (longueur x largeur x hauteur) | D46: Surface plateforme (m²)
B47: 30 | C47: 7,95 x 4,44 x 1,3 m | D47: 35
B48: 60 | C48: 8,1 x 7,4 x 1,5 m | D48: 60
B49: 120 | C49: 11,7 x 9,3 x 1 m | D49: 104
B50: 240 | C50: 10,4 x 18,5 x 1,6 m | D50: 192
B51: Compter une aire d'aspiration de 32m² (8 x 4m)
F53: Bennes déchets | I53: Stockage modules
E54: Nombre min | F54: 3 | H54: Nombre de modules | I54: 0
E55: Volume unitaire (m3) | F55: 20 | H55: Surface à prévoir (à 50m² près au supérieur) | I55: =I54*10*((2.382+0.15)*(1.134+0.15))/720 -> 0
C56: Base vie | E56: Surface unitaire (m²) | F56: =3*5 -> 15
C57: Surface conseillée (m²)
B58: P <= 10MWc | C58: 1000
B59: P > 10MWc | C59: 1500

Sheet Batteries de stockage
D3: POUR TOUS LES PROJETS
D4: Conteneur 20 pieds (6x3x3m) | E4: PTR
C5: P<=20MWc | D5: x4 | E5: x2
C6: P>20MWc | D6: x8 | E6: x4
B9: Règles ICPE
B10: Implantation à 12m de la clôture
B11: Equipements espacés de 7m les uns par rapport aux autres
B13: PROJETS A ENJEUX
B14: 1 conteneur 20 pieds et 1 PTR associé (capacité 5MWh)

Sheet 4.a Revue ESQ
C3: ='2. Caractéristiques du projet'!A1 -> Projet Saint-Cyr-en-Val
C5: Chargé de projet - dév : | E5: PHU
C6: Chargé de projet - étude : | E6: LEL
C8: Design
C9: Pnom | F9: Productible PVSyst | I9: Performance Ratio (PR) | L9: Production (P50)
C10: =OFFSET('2. Caractéristiques du projet'!B39,0,MATCH(MAX('2. Caractéristiques du projet'!B39:Z39)+1,'2. Caractéristiques du projet'!B39:Z39,1)-1) -> 2.93878 | F10: =OFFSET('2. Caractéristiques du projet'!B165,0,MATCH(MAX('2. Caractéristiques du projet'!B165:Z165)+1,'2. Caractéristiques du projet'!B165:Z165,1)-1) -> 1198 | I10: =OFFSET('2. Caractéristiques du projet'!B166,0,MATCH(MAX('2. Caractéristiques du projet'!B166:Z166)+1,'2. Caractéristiques du projet'!B166:Z166,1)-1) -> 0.8995 | L10: =OFFSET('2. Caractéristiques du projet'!B167,0,MATCH(MAX('2. Caractéristiques du projet'!B167:Z167)+1,'2. Caractéristiques du projet'!B167:Z167,1)-1) -> 3.5206584
J12: Documents à disposition
J13: Topo IGN : | K13: FALSE | L13: DT : | M13: TRUE
J14: Plan de masse : | K14: TRUE | L14: Rés. Privés : | M14: TRUE
J15: Plan de coupe : | K15: TRUE | L15: Dép Ouvr GRD :
J16: PVSyst : | K16: TRUE | L16: Unifilaire :
J19: Module APD
J20: Dim (mm) : | K20: 2382x1134x30 | L20: Puissance : | M20: =OFFSET('2. Caractéristiques du projet'!B33,0,MATCH(MAX('2. Caractéristiques du projet'!B33:Z33)+1,'2. Caractéristiques du projet'!B33:Z33,1)-1) -> 635
J21: Techno : | K21: TopCon | L21: .pan : | M21: TRUE
J22: Date 1er Livraison : | K22: Q3 2028
C30: Remarques : Objectif de 2,99MWc installés pour demander un cas par cas. Réduction du nombre de tables,augmentation de l'inter-table. Critère NZIA CRE + début de chantier avant 2030 => modules de 635Wc max.

Sheet 4.b Revue APS
C3: ='2. Caractéristiques du projet'!A1 -> Projet Saint-Cyr-en-Val
C5: Chargé de projet - dév : | E5: PHU
C6: Chargé de projet - étude : | E6: LEL
C8: Design
C9: Pnom | F9: Productible PVSyst | I9: Performance Ratio (PR) | L9: Production (P50)
C10: =OFFSET('2. Caractéristiques du projet'!B39,0,MATCH(MAX('2. Caractéristiques du projet'!B39:Z39)+1,'2. Caractéristiques du projet'!B39:Z39,1)-1) -> 2.93878 | F10: =OFFSET('2. Caractéristiques du projet'!B165,0,MATCH(MAX('2. Caractéristiques du projet'!B165:Z165)+1,'2. Caractéristiques du projet'!B165:Z165,1)-1) -> 1198 | I10: =OFFSET('2. Caractéristiques du projet'!B166,0,MATCH(MAX('2. Caractéristiques du projet'!B166:Z166)+1,'2. Caractéristiques du projet'!B166:Z166,1)-1) -> 0.8995 | L10: =OFFSET('2. Caractéristiques du projet'!B167,0,MATCH(MAX('2. Caractéristiques du projet'!B167:Z167)+1,'2. Caractéristiques du projet'!B167:Z167,1)-1) -> 3.5206584
J12: Documents à disposition
J13: Topo Drone : | K13: FALSE | L13: DT : | M13: FALSE
J14: Plan de masse : | K14: FALSE | L14: Rés. Privés : | M14: FALSE
J15: Plan de coupe : | K15: FALSE | L15: Dép Ouvr GRD :
J16: PVSyst : | K16: FALSE | L16: Unifilaire :
J19: Module APD
J20: Dim (mm) : | K20: 2382x1134x30 | L20: Puissance : | M20: =OFFSET('2. Caractéristiques du projet'!B33,0,MATCH(MAX('2. Caractéristiques du projet'!B33:Z33)+1,'2. Caractéristiques du projet'!B33:Z33,1)-1) -> 635
J21: Techno : | K21: TopCon | L21: .pan : | M21: TRUE
J22: Date 1er Livraison : | K22: Q2 2028
C30: Remarque :

Sheet 4.c Revue APD
C3: ='2. Caractéristiques du projet'!A1 -> Projet Saint-Cyr-en-Val
C5: Chargé de projet - dév :
C6: Chargé de projet - étude : | E6: xxx
C8: Design
C9: Pnom | F9: Productible PVSyst | I9: Performance Ratio (PR) | L9: Production (P50)
C10: =OFFSET('2. Caractéristiques du projet'!B39,0,MATCH(MAX('2. Caractéristiques du projet'!B39:Z39)+1,'2. Caractéristiques du projet'!B39:Z39,1)-1) -> 2.93878 | F10: =OFFSET('2. Caractéristiques du projet'!B165,0,MATCH(MAX('2. Caractéristiques du projet'!B165:Z165)+1,'2. Caractéristiques du projet'!B165:Z165,1)-1) -> 1198 | I10: =OFFSET('2. Caractéristiques du projet'!B166,0,MATCH(MAX('2. Caractéristiques du projet'!B166:Z166)+1,'2. Caractéristiques du projet'!B166:Z166,1)-1) -> 0.8995 | L10: =OFFSET('2. Caractéristiques du projet'!B167,0,MATCH(MAX('2. Caractéristiques du projet'!B167:Z167)+1,'2. Caractéristiques du projet'!B167:Z167,1)-1) -> 3.5206584
J12: Documents à disposition
J13: Topo Géomètre : | K13: FALSE | L13: DT : | M13: FALSE
J14: Plan de masse : | K14: FALSE | L14: Rés. Privés : | M14: FALSE
J15: Plan de coupe : | K15: FALSE | L15: Dép Ouvr GRD : | M15: FALSE
J16: PVSyst : | K16: FALSE | L16: Unifilaire : | M16: FALSE
J18: Ratio DC/AC
J19: PDC : | K19: =OFFSET('2. Caractéristiques du projet'!B39,0,MATCH(MAX('2. Caractéristiques du projet'!B39:Z39)+1,'2. Caractéristiques du projet'!B39:Z39,1)-1) -> 2.93878 | L19: Pinj VA (si bridage) : | M19: /
J20: PAC : | K20: 7.2 | L20: Rat. DC/AC : | M20: =IF(M19="/",K19/K20,K19/M19) -> 0.40816389
J21: ηDesign :
J23: Module APD
J24: Dim (mm) : | K24: 2382x1134x30 | L24: Puissance : | M24: =OFFSET('2. Caractéristiques du projet'!B33,0,MATCH(MAX('2. Caractéristiques du projet'!B33:Z33)+1,'2. Caractéristiques du projet'!B33:Z33,1)-1) -> 635
J25: Techno : | K25: TopCon | L25: .pan : | M25: TRUE
J26: Date 1er Livraison : | K26: Q2 2028
C30: Remarque :

Sheet 5. Passation Dev-Constru
